tree_sitter_comment/__init__.py
tree_sitter_comment/__init__.pyi
tree_sitter_comment/_binding.abi3.so
tree_sitter_comment/binding.c
tree_sitter_comment/py.typed
tree_sitter_comment-0.3.0.dist-info/METADATA
tree_sitter_comment-0.3.0.dist-info/WHEEL
tree_sitter_comment-0.3.0.dist-info/top_level.txt
tree_sitter_comment-0.3.0.dist-info/RECORD
tree_sitter_comment-0.3.0.dist-info/licenses/LICENSE
