Metadata-Version: 2.4
Name: tree-sitter-comment
Version: 0.3.0
Summary: Grammar for code tags like TODO:, FIXME(user): for the tree-sitter parsing library
Author-email: Santos Gallegos <stsewd@proton.me>
License: MIT
Project-URL: Homepage, https://github.com/stsewd/tree-sitter-comment
Project-URL: Funding, https://github.com/sponsors/stsewd
Keywords: incremental,parsing,tree-sitter,comment
Classifier: Intended Audience :: Developers
Classifier: Topic :: Software Development :: Compilers
Classifier: Topic :: Text Processing :: Linguistic
Classifier: Typing :: Typed
Requires-Python: >=3.10
License-File: LICENSE
Provides-Extra: core
Requires-Dist: tree-sitter~=0.24; extra == "core"
Dynamic: license-file
